kaskade/__init__.py
kaskade/admin.py
kaskade/banner.py
kaskade/colors.py
kaskade/configs.py
kaskade/consumer.py
kaskade/deserializers.py
kaskade/main.py
kaskade/models.py
kaskade/services.py
kaskade/styles.css
kaskade/unicodes.py
kaskade/utils.py
kaskade-4.0.6.dist-info/METADATA
kaskade-4.0.6.dist-info/WHEEL
kaskade-4.0.6.dist-info/entry_points.txt
kaskade-4.0.6.dist-info/licenses/LICENSE
kaskade-4.0.6.dist-info/RECORD
