Metadata-Version: 2.4
Name: kaskade
Version: 4.0.6
Summary: kaskade is a text user interface for kafka
License: MIT
License-File: LICENSE
Keywords: kafka,kaskade
Author: Saúl Piña
Author-email: sauljabin@gmail.com
Requires-Python: >=3.10,<3.15
Classifier: License :: OSI Approved :: MIT License
Classifier: Environment :: Console
Classifier: Operating System :: MacOS
Classifier: Operating System :: Unix
Classifier: Programming Language :: Python :: 3.10
Classifier: Programming Language :: Python :: 3.11
Classifier: Programming Language :: Python :: 3.12
Classifier: Programming Language :: Python :: 3.13
Classifier: Programming Language :: Python :: 3.14
Requires-Dist: cloup (>=3.0)
Requires-Dist: confluent-kafka[avro,json,protobuf] (>=2.12)
Requires-Dist: textual (>=6.5)
Project-URL: Documentation, https://github.com/sauljabin/kaskade
Project-URL: Homepage, https://github.com/sauljabin/kaskade
Project-URL: Repository, https://github.com/sauljabin/kaskade
Project-URL: changelog, https://github.com/sauljabin/kaskade/blob/main/CHANGELOG.md
Project-URL: funding, https://github.com/sponsors/sauljabin
Project-URL: issues, https://github.com/sauljabin/kaskade/issues
